Workbook

Sheet README
A1: This spreadsheet summarizes: 1) my validation of the economic damage data inputs used in Glennerster, Snyder and Tan (2023). Original values are taken from the "economic harm projections 06" spreadsheet. Reported sources are found in Table I of the abovementioned paper. 2) My attempt at updating our economic damage inputs given my review of the sources. I then use the updated estimates to fit a model on SMUs and economic losses. 3) Global GDP and US CPI data that we use to estimate and normalize total GDP loss estimates.

Sheet Validation
A1: Original values in Glennerster, Snyder, and Tan (2023) | H1: Notes
A2: Disease | B2: Start Date | C2: Emd Date | D2: Duration | E2: Mortality | F2: GDP Losses per Year (bil $) | G2: GDP proportional loss per year | H2: Mortality source | I2: Economic loss source | J2: Notes on values
A3: Zika | B3: 2015 | C3: 2017 | D3: 3 | E3: 1000 | F3: 15 | G3: 0.000167 | H3: Set at minimum detectable Marani et al. (2021) value | I3: UNDP report (offline) | J3: It looks like values have been taken from Table 2, Annex 8. I'm not sure where $15 billion annual economic loss number is from in the report. I think percentage GDP numbers are expressed as a share of LAC and Caribbean GDP, not global.
A4: SARS | B4: 2002 | C4: 2003 | D4: 2 | E4: 1000 | F4: 11 | G4: 0.00025 | H4: Set at minimum detectable Marani et al. (2021) value | I4: Keogh-brown et al (2008) | J4: Roughly sum of lower GPD loss values in Table 4
A5: Ebola | B5: 2014 | C5: 2014 | D5: 1 | E5: 11325 | F5: 72 | G5: 0.00083 | H5: CDC | I5: Huber, Finelli, and Stevens (2018) | J5: Ebola deaths are deaths directly attributable to infection; other sources use excess deaths. One paper estimates excess deaths from other diseases. Huber et al. paper reports $53 billion estimate -- maybe $72 billion is after adjusting for inflation? $53 billion estimate also includes costs of mortality for other diseases, so this number seems inappropriate. We can subset to just economic losses.
A6: Covid-19 | B6: 2020 | C6: 2022 | D6: 3 | E6: 21300000 | F6: 3151 | G6: 0.036 | H6: Economist global excess death model | I6: IMF 2022 | J6: Economist may have slightly updated numbers, so we should update; Can't find absolute or reported % GDP loss number in IMF reference (reported % GDP loss is 14.4%). Also note that there is potentially an error in the proportional GDP loss (should be 14.4%/3 = 4.8%, not 14.4%/4 = 3.6%).
A7: 1918 flu | B7: 1918 | C7: 1920 | D7: 3 | E7: 32000000 | F7: 1751 | G7: 0.02 | H7: Patterson and Pyle (1991) | I7: Barro, Ursua, and Weng | J7: Other sources noted by OWID have lower mortality estimates (~1/2); Proportional GDP loss retrieved by dividing total %GDP loss by duration.

Sheet Updated numbers
A1: Disease | B1: Start Date | C1: Emd Date | D1: Duration | E1: Mortality | F1: Mortality (SMU) | G1: Intensity (SMU) | H1: GDP loss year | I1: GDP loss valuation year | J1: Total GDP losses (valuation year value) | K1: Total GDP losses (reference year value, 2022 dollars) | L1: Fraction GDP losses | M1: Annual fraction GPD losses | N1: Mortality source | O1: Economic loss source | P1: Notes on values | Q1: Other notes
A2: Zika | B2: 2015 | C2: 2017 | D2: =C2-B2+1 -> 3 | F2: 5.59913e-05 | G2: =F2/D2 -> 1.8663767e-05 | H2: 2015 | I2: 2015 | J2: =7*1000000000 -> 7000000000 | K2: =J2*(VLOOKUP(Constants!$B$1,'US CPI'!$A$2:$B$114,2,FALSE)/VLOOKUP(I2,'US CPI'!$A$2:$B$114,2,FALSE)) -> 8645147679 | L2: =K2/VLOOKUP(H2,'Global GDP over time'!$C$1:$E$49,3,FALSE) -> 6.350211e-05 | M2: =L2/D2 -> 2.116737e-05 | N2: Global Burden of Disease Collaborative Network. Global Burden of Disease Study 2021 (GBD 2021) Results. Seattle, United States: Institute for Health Metrics and Evaluation (IHME), 2022. Available from https://vizhub.healthdata.org/gbd-results/. | O2: UNDP report (offline) | P2: Mortality loss: sum of global deaths per 100,000 for 2015, 16 and 17 Economic loss: takes lower economic estimate from Annex 2, table 8. | Q2: Can maybe update to specific SMUs using Ganqi data. Should we still include given below SMU threshold?
A3: SARS | B3: 2002 | C3: 2003 | D3: =C3-B3+1 -> 2 | F3: 0.0011659276 | G3: =F3/D3 -> 0.00058296381 | H3: 2005 | I3: 2005 | J3: =11.8*1000000000 -> 11800000000 | K3: =J3*(VLOOKUP(Constants!$B$1,'US CPI'!$A$2:$B$114,2,FALSE)/VLOOKUP(I3,'US CPI'!$A$2:$B$114,2,FALSE)) -> 17684895033 | L3: =K3/VLOOKUP(H3,'Global GDP over time'!$C$1:$E$49,3,FALSE) -> 0.00018081696 | M3: =L3/D3 -> 9.0408482e-05 | N3: Marani et al. (2021) value | O3: Keogh-brown et al (2008) | P3: Sum of lower GPD loss values in Table 4. Unclear denomination year
A4: Ebola | B4: 2013 | C4: 2016 | D4: =C4-B4+1 -> 4 | E4: 11325 | F4: 0.0157 | G4: =F4/D4 -> 0.003925 | H4: 2014 | I4: 2014 | J4: =15.67*3*1000000000 -> 47010000000 | K4: =J4*(VLOOKUP(Constants!$B$1,'US CPI'!$A$2:$B$114,2,FALSE)/VLOOKUP(I4,'US CPI'!$A$2:$B$114,2,FALSE)) -> 58131926489 | L4: =K4/VLOOKUP(H4,'Global GDP over time'!$C$1:$E$49,3,FALSE) -> 0.00043854314 | M4: =L4/D4 -> 0.00010963579 | N4: Marani et al. (Ganqi note) | O4: Huber, Finelli, and Stevens (2018) | P4: Sums direct economics costs, treatment and screening costs, and cost of human resources deployment in Huber, Finelli, and Stevens. Multiplies by three to account for three year duration
A5: Covid-19 | B5: 2020 | C5: 2024 | D5: =C5-B5+1 -> 5 | E5: 21300000 | F5: 4.59 | G5: =F5/D5 -> 0.918 | H5: 2019 | I5: 2019 | J5: =13800000000000 -> 13800000000000 | K5: =J5*(VLOOKUP(Constants!$B$1,'US CPI'!$A$2:$B$114,2,FALSE)/VLOOKUP(I5,'US CPI'!$A$2:$B$114,2,FALSE)) -> 15796871333594 | L5: =K5/VLOOKUP(H5,'Global GDP over time'!$C$1:$E$49,3,FALSE) -> 0.10097651 | M5: =L5/D5 -> 0.020195303 | N5: Economist global excess death model | O5: IMF 2022, Other IMF report | P5: Total GDP loss value stated in Agarwal and Gopinath.
A6: 1918 flu | B6: 1918 | C6: 1920 | D6: =C6-B6+1 -> 3 | E6: 32000000 | F6: 171 | G6: =F6/D6 -> 57 | H6: 1917 | I6: =Constants!$B$1 -> 2022 | J6: =L6*VLOOKUP(H6, 'Global GDP over time'!$C$1:$E$49,3,TRUE) -> 300223500612 | K6: =J6*(VLOOKUP(Constants!$B$1,'US CPI'!$A$2:$B$114,2,FALSE)/VLOOKUP(I6,'US CPI'!$A$2:$B$114,2,FALSE)) -> 300223500612 | L6: 0.06 | M6: =L6/D6 -> 0.02 | N6: Patterson and Pyle (1991) | O6: Barro, Ursua, and Weng | P6: Other sources noted by OWID have lower mortality estimates (~1/2).
A7: Asian flu
A8: Hong kong flu | B8: 1968 | C8: 1970 | D8: =C8-B8+1 -> 3 | F8: 2.82 | G8: =F8/D8 -> 0.94 | H8: ='Global GDP over time'!$I$4 -> 2017 | I8: =Constants!$B$1 -> 2022 | J8: =L8*VLOOKUP(H8, 'Global GDP over time'!$C$1:$E$49,3,TRUE) -> 3525297429621 | K8: =J8*(VLOOKUP(Constants!$B$1,'US CPI'!$A$2:$B$114,2,FALSE)/VLOOKUP(I8,'US CPI'!$A$2:$B$114,2,FALSE)) -> 3525297429621 | L8: 0.024 | M8: =L8/D8 -> 0.008 | N8: Marani et al. (Ganqi note) | O8: Jinjarak et al. (2022)
A9: Swine flu

Sheet Global GDP over time
A1: Entity | B1: Code | C1: Year | D1: GDP (raw data) | E1: GDP (2022 valuation) | H1: Source | I1: Notes
A2: World | B2: OWID_WRL | C2: 1 | D2: 213000000000 | E2: =D2*(VLOOKUP(Constants!$B$1,'US CPI'!$A$3:$B$114,2,FALSE)/VLOOKUP($I$4,'US CPI'!$A$3:$B$114,2,FALSE)) -> 254365973072 | H2: Our World in Data | I2: Expressed in 2017 International $
A3: World | B3: OWID_WRL | C3: 1000 | D3: 246000000000 | E3: =D3*(VLOOKUP(Constants!$B$1,'US CPI'!$A$3:$B$114,2,FALSE)/VLOOKUP($I$4,'US CPI'!$A$3:$B$114,2,FALSE)) -> 293774785802
A4: World | B4: OWID_WRL | C4: 1500 | D4: 503000000000 | E4: =D4*(VLOOKUP(Constants!$B$1,'US CPI'!$A$3:$B$114,2,FALSE)/VLOOKUP($I$4,'US CPI'!$A$3:$B$114,2,FALSE)) -> 600685842513 | H4: Reference year value | I4: 2017
A5: World | B5: OWID_WRL | C5: 1600 | D5: 671000000000 | E5: =D5*(VLOOKUP(Constants!$B$1,'US CPI'!$A$3:$B$114,2,FALSE)/VLOOKUP($I$4,'US CPI'!$A$3:$B$114,2,FALSE)) -> 801312525500
A6: World | B6: OWID_WRL | C6: 1700 | D6: 752000000000 | E6: =D6*(VLOOKUP(Constants!$B$1,'US CPI'!$A$3:$B$114,2,FALSE)/VLOOKUP($I$4,'US CPI'!$A$3:$B$114,2,FALSE)) -> 898043247654
A7: World | B7: OWID_WRL | C7: 1820 | D7: 1400000000000 | E7: =D7*(VLOOKUP(Constants!$B$1,'US CPI'!$A$3:$B$114,2,FALSE)/VLOOKUP($I$4,'US CPI'!$A$3:$B$114,2,FALSE)) -> 1671889024888
A8: World | B8: OWID_WRL | C8: 1850 | D8: 1850000000000 | E8: =D8*(VLOOKUP(Constants!$B$1,'US CPI'!$A$3:$B$114,2,FALSE)/VLOOKUP($I$4,'US CPI'!$A$3:$B$114,2,FALSE)) -> 2209281925745
A9: World | B9: OWID_WRL | C9: 1870 | D9: 2350000000000 | E9: =D9*(VLOOKUP(Constants!$B$1,'US CPI'!$A$3:$B$114,2,FALSE)/VLOOKUP($I$4,'US CPI'!$A$3:$B$114,2,FALSE)) -> 2806385148919
A10: World | B10: OWID_WRL | C10: 1900 | D10: 4190000000000 | E10: =D10*(VLOOKUP(Constants!$B$1,'US CPI'!$A$3:$B$114,2,FALSE)/VLOOKUP($I$4,'US CPI'!$A$3:$B$114,2,FALSE)) -> 5003725010200
A11: World | B11: OWID_WRL | C11: 1920 | D11: 5770000000000 | E11: =D11*(VLOOKUP(Constants!$B$1,'US CPI'!$A$3:$B$114,2,FALSE)/VLOOKUP($I$4,'US CPI'!$A$3:$B$114,2,FALSE)) -> 6890571195430
A12: World | B12: OWID_WRL | C12: 1940 | D12: 9140000000000 | E12: =D12*(VLOOKUP(Constants!$B$1,'US CPI'!$A$3:$B$114,2,FALSE)/VLOOKUP($I$4,'US CPI'!$A$3:$B$114,2,FALSE)) -> 10915046919625
A13: World | B13: OWID_WRL | C13: 1950 | D13: 10100000000000 | E13: =D13*(VLOOKUP(Constants!$B$1,'US CPI'!$A$3:$B$114,2,FALSE)/VLOOKUP($I$4,'US CPI'!$A$3:$B$114,2,FALSE)) -> 12061485108119
A14: World | B14: OWID_WRL | C14: 1960 | D14: 15900000000000 | E14: =D14*(VLOOKUP(Constants!$B$1,'US CPI'!$A$3:$B$114,2,FALSE)/VLOOKUP($I$4,'US CPI'!$A$3:$B$114,2,FALSE)) -> 18987882496940
A15: World | B15: OWID_WRL | C15: 1970 | D15: 26200000000000 | E15: =D15*(VLOOKUP(Constants!$B$1,'US CPI'!$A$3:$B$114,2,FALSE)/VLOOKUP($I$4,'US CPI'!$A$3:$B$114,2,FALSE)) -> 31288208894329
A16: World | B16: OWID_WRL | C16: 1980 | D16: 38200000000000 | E16: =D16*(VLOOKUP(Constants!$B$1,'US CPI'!$A$3:$B$114,2,FALSE)/VLOOKUP($I$4,'US CPI'!$A$3:$B$114,2,FALSE)) -> 45618686250510
... A49: World | B49: OWID_WRL | C49: 2022 | D49: 139000000000000 | E49: =D49*(VLOOKUP(Constants!$B$1,'US CPI'!$A$3:$B$114,2,FALSE)/VLOOKUP($I$4,'US CPI'!$A$3:$B$114,2,FALSE)) -> 165994696042432

Sheet Constants
A1: Project reference year | B1: 2022

Sheet US CPI
A1: Raw | E1: Constructed | I1: Source
A2: Year | B2: CPI (Urban) | C2: Avg percent change (inflation) | E2: Year | F2: Deflator | I2: Minneapolis Fed
A3: 1913 | B3: 9.9 | E3: =A3 -> 1913 | F3: =VLOOKUP(E3,$A$3:$B$114,2,FALSE)/VLOOKUP($J$3,$A$3:$B$114,2,FALSE) -> 0.033823027 | I3: Deflator reference year | J3: 2022
A4: 1914 | B4: 10 | C4: 0.013 | E4: =A4 -> 1914 | F4: =VLOOKUP(E4,$A$3:$B$114,2,FALSE)/VLOOKUP($J$3,$A$3:$B$114,2,FALSE) -> 0.034164674
A5: 1915 | B5: 10.1 | C5: 0.009 | E5: =A5 -> 1915 | F5: =VLOOKUP(E5,$A$3:$B$114,2,FALSE)/VLOOKUP($J$3,$A$3:$B$114,2,FALSE) -> 0.03450632
A6: 1916 | B6: 10.9 | C6: 0.077 | E6: =A6 -> 1916 | F6: =VLOOKUP(E6,$A$3:$B$114,2,FALSE)/VLOOKUP($J$3,$A$3:$B$114,2,FALSE) -> 0.037239494
A7: 1917 | B7: 12.8 | C7: 0.178 | E7: =A7 -> 1917 | F7: =VLOOKUP(E7,$A$3:$B$114,2,FALSE)/VLOOKUP($J$3,$A$3:$B$114,2,FALSE) -> 0.043730782
A8: 1918 | B8: 15 | C8: 0.173 | E8: =A8 -> 1918 | F8: =VLOOKUP(E8,$A$3:$B$114,2,FALSE)/VLOOKUP($J$3,$A$3:$B$114,2,FALSE) -> 0.051247011
A9: 1919 | B9: 17.3 | C9: 0.152 | E9: =A9 -> 1919 | F9: =VLOOKUP(E9,$A$3:$B$114,2,FALSE)/VLOOKUP($J$3,$A$3:$B$114,2,FALSE) -> 0.059104886
A10: 1920 | B10: 20 | C10: 0.156 | E10: =A10 -> 1920 | F10: =VLOOKUP(E10,$A$3:$B$114,2,FALSE)/VLOOKUP($J$3,$A$3:$B$114,2,FALSE) -> 0.068329347
A11: 1921 | B11: 17.9 | C11: -0.109 | E11: =A11 -> 1921 | F11: =VLOOKUP(E11,$A$3:$B$114,2,FALSE)/VLOOKUP($J$3,$A$3:$B$114,2,FALSE) -> 0.061154766
A12: 1922 | B12: 16.8 | C12: -0.062 | E12: =A12 -> 1922 | F12: =VLOOKUP(E12,$A$3:$B$114,2,FALSE)/VLOOKUP($J$3,$A$3:$B$114,2,FALSE) -> 0.057396652
A13: 1923 | B13: 17.1 | C13: 0.018 | E13: =A13 -> 1923 | F13: =VLOOKUP(E13,$A$3:$B$114,2,FALSE)/VLOOKUP($J$3,$A$3:$B$114,2,FALSE) -> 0.058421592
A14: 1924 | B14: 17.1 | C14: 0.004 | E14: =A14 -> 1924 | F14: =VLOOKUP(E14,$A$3:$B$114,2,FALSE)/VLOOKUP($J$3,$A$3:$B$114,2,FALSE) -> 0.058421592
A15: 1925 | B15: 17.5 | C15: 0.024 | E15: =A15 -> 1925 | F15: =VLOOKUP(E15,$A$3:$B$114,2,FALSE)/VLOOKUP($J$3,$A$3:$B$114,2,FALSE) -> 0.059788179
... A114: 2024 | B114: 314.4 | C114: 0.032 | E114: =A114 -> 2024 | F114: =VLOOKUP(E114,$A$3:$B$114,2,FALSE)/VLOOKUP($J$3,$A$3:$B$114,2,FALSE) -> 1.0741373
